pytoolbox/__init__.py
pytoolbox/config.py
pytoolbox/file_system.py
pytoolbox/folder.py
pytoolbox/json.py
tests/__init__.py
tests/test_ensure_folder_exists.py
tests/test_json_functions.py
atari_monk_pytoolbox-0.1.2.dist-info/METADATA
atari_monk_pytoolbox-0.1.2.dist-info/WHEEL
atari_monk_pytoolbox-0.1.2.dist-info/top_level.txt
atari_monk_pytoolbox-0.1.2.dist-info/RECORD
