Metadata-Version: 2.1
Name: atari-monk-pytoolbox
Version: 0.1.2
Summary: A tools package.
Home-page: https://github.com/atari-monk/pytoolbox
Author: atari monk
Author-email: atari.monk1@gmail.com
Classifier: Programming Language :: Python :: 3
Classifier: License :: OSI Approved :: MIT License
Requires-Python: >=3.12.0
Requires-Dist: atari-monk-cli-logger
